Workbook

Sheet Cover & Instructions
B2: Android Penetration Testing Master Checklist
B3: 2026 Edition — Deduplicated across 20+ sources + 2024-2026 cutting-edge research
B5: Coverage
B6: • 373 unique test cases across 20 categories
B7: • Full OWASP MASVS/MASTG coverage: MASVS-STORAGE, CRYPTO, AUTH, NETWORK, PLATFORM, CODE, RESILIENCE, PRIVACY
B8: • Even coverage across layers: Static Analysis, Dynamic Analysis, Runtime Manipulation, Network, IPC, Storage, WebView, Backend
B9: • 2024-2026 vectors most checklists miss: Pixnapping (CVE-2025-48561), TapTrap (USENIX Security 2025), Dirty Stream (CVE-2024-0044), Zygote injection (CVE-2024-31317), Play Integrity/TrickyStore bypass, Flutter/Hermes/Unity IL2CPP reverse engineering
B10: • Cross-platform framework coverage: React Native (Hermes/hbctool), Flutter (reFlutter/BoringSSL), Unity IL2CPP, Xamarin/pyxamstore, Cordova, .NET MAUI 9
B11: • Sourced from: OWASP MASTG, HackTricks, PortSwigger, Oversecured, TrustedSec, Promon, Praetorian, TU Wien (TapTrap), Meta Red Team X, and 20+ other authoritative resources
B13: How to use
B14: 1. Go to 'Master Checklist' — every test case has Test ID, Category, Test Case, Approach, Payloads/Tooling, References, Severity.
B15: 2. Set status per test in column H via the dropdown (Not Started / In Progress / Pass / Fail / N/A). Conditional formatting colors the rows.
... B29: Use only on systems and apps you are authorized to test. Several techniques (repackaging, runtime manipulation, IPC fuzzing) may violate terms of service and require explicit written authorization. Verify CVE applicability against the target's Android version and Security Patch Level before reporting. Payloads are representative; tune to the specific stack and framework.

Sheet Master Checklist
A1: Android Pentesting Master Checklist
A2: Set Status in column H. Filter using header row 3. Severity is color-coded.
A3: Test ID | B3: Category | C3: Test Case / Attack Vector | D3: Approach to Exploit | E3: Payloads / Tooling | F3: References | G3: Severity | H3: Status | I3: Notes / Evidence
A4: AND-01-001 | B4: Reconnaissance & Information Gathering | C4: APK acquisition via adb pull | D4: Pull the installed APK (including split APKs) directly from a device to guarantee analysis of the exact build the target is running. Store/mirror versions may differ from what was actually shipped. | E4: adb shell pm path com.target | adb pull /data/app/.../base.apk | For splits: adb shell pm path --show-versioncode com.target | F4: developer.android.com | hacktricks.wiki | G4: Info | H4: Not Started
A5: AND-01-002 | B5: Reconnaissance & Information Gathering | C5: APK acquisition from mirrors | D5: Compare Play Store, APKMirror, and APKPure builds for version drift, staged rollouts, and unpatched historical endpoints. | E5: apkeep -a com.target ./ | Manual download from apkmirror.com / apkpure.com | Diff base.apk + split_*.apk | F5: getastra.com | apkeep github | G5: Info | H5: Not Started
A6: AND-01-003 | B6: Reconnaissance & Information Gathering | C6: Wayback / historical APK archives | D6: Retrieve older APKs from archive.org and APK archive mirrors to find removed debug endpoints, reintroduced bugs, or leaked keys in previous versions. | E6: archive.org search: com.target apk | Historical APK sites: apkfollow, aptoide old versions | F6: indusface.com | G6: Low | H6: Not Started
A7: AND-01-004 | B7: Reconnaissance & Information Gathering | C7: Declared vs used permissions diff | D7: Enumerate all manifest permissions and correlate against actual API usage to identify over-privilege and orphan permissions (a common finding in security audits). | E7: aapt dump permissions base.apk | jadx grep for permission-gated Android API calls | mobsf permissions report | F7: OWASP MASTG | Hrishikesh7665 checklist | G7: Medium | H7: Not Started
A8: AND-01-005 | B8: Reconnaissance & Information Gathering | C8: Exported component enumeration | D8: List all exported activities, services, broadcast receivers, and content providers as the primary IPC attack surface. | E8: drozer: run app.package.attacksurface com.target | run app.activity.info -a com.target | aapt dump xmltree base.apk AndroidManifest.xml | F8: Hrishikesh7665 checklist | drozer docs | G8: Medium | H8: Not Started
A9: AND-01-006 | B9: Reconnaissance & Information Gathering | C9: Hardcoded URL / endpoint extraction | D9: Extract backend hosts, S3 buckets, GraphQL endpoints, and API bases from strings, resources, and DEX to enrich the backend attack surface. | E9: apkleaks -f base.apk | strings -a classes.dex | grep -E 'https?://' | jadx grep -r for URL patterns | F9: github.com/dwisiswant0/apkleaks | Hrishikesh7665 | G9: Medium | H9: Not Started
A10: AND-01-007 | B10: Reconnaissance & Information Gathering | C10: Third-party library fingerprinting | D10: Identify SDK names/versions to map to known CVEs and known-bad configurations (weak defaults, exposed keys). | E10: apkid base.apk | LibScout with signature DB | jadx package tree review | Snyk mobile scanner | F10: github.com/rednaga/APKiD | martian1337 notes | G10: Medium | H10: Not Started
A11: AND-01-008 | B11: Reconnaissance & Information Gathering | C11: Native library discovery & ABI enumeration | D11: Enumerate .so files and supported ABIs to scope native code review; look for stripped vs unstripped, custom native libs, and JNI entry points. | E11: unzip -l base.apk | grep lib/ | file lib/arm64-v8a/*.so | nm -D lib/arm64-v8a/libnative.so | F11: ivan-sincek cheat sheet | withsecure labs | G11: Info | H11: Not Started
A12: AND-01-009 | B12: Reconnaissance & Information Gathering | C12: Firebase project discovery | D12: Extract Firebase config to test RTDB/Firestore/Remote Config/Storage exposure — a consistent high-severity finding across bug bounty programs. | E12: grep -r firebase base_apktool/res/values/strings.xml | Read assets/google-services.json | Extract project_id, api_key, database_url | F12: medium.com/@xelcezeri | jsmon.sh | G12: High | H12: Not Started
A13: AND-01-010 | B13: Reconnaissance & Information Gathering | C13: Analytics / SDK key leakage | D13: Extract AppsFlyer, Mixpanel, Amplitude, Adjust, Branch keys usable for data poisoning, event forgery, or user PII extraction via SDK admin APIs. | E13: grep -r strings.xml for _API_KEY, dev_key, sdk_key | Manifest meta-data tags | F13: oversecured.com | jsmon.sh | G13: Medium | H13: Not Started
A14: AND-01-011 | B14: Reconnaissance & Information Gathering | C14: GitHub / OSINT for package name | D14: Search public repositories for the package for leaked keystores, backend credentials, test config files, and internal documentation. | E14: GitHub code search: com.target | Search for firebaseio, apikey with package | trufflehog scan of repo mentions | F14: jsmon.sh | github search | G14: Medium | H14: Not Started
A15: AND-01-012 | B15: Reconnaissance & Information Gathering | C15: Certificate transparency on backend hosts | D15: Enumerate subdomains of extracted API hosts via CT logs — often surfaces staging, dev, admin, or legacy hosts not linked from production. | E15: crt.sh?q=%.target.com | curl https://crt.sh/?q=target.com&output=json | jq -r '.[].name_value' | sort -u | F15: indusface.com | crt.sh | G15: Low | H15: Not Started
... A376: AND-20-015 | B376: Backend API Security (Mobile-Specific) | C376: Server-side proof of freshness / nonce absent | D376: Backend accepts requests without nonce or timestamp — replay attacks work. | E376: Capture request | Replay hours/days later | Test if action still succeeds | F376: OWASP API Security | RFC 6819 | G376: Medium | H376: Not Started

Sheet Summary by Category
A1: Summary by Category
A3: Category | B3: Total | C3: Not Started | D3: In Progress | E3: Pass | F3: Fail | G3: % Complete
A4: Reconnaissance & Information Gathering | B4: =COUNTIF('Master Checklist'!$B$4:$B$376,A4) -> 27 | C4: =COUNTIFS('Master Checklist'!$B$4:$B$376,A4,'Master Checklist'!$H$4:$H$376,"Not Started") -> 27 | D4: =COUNTIFS('Master Checklist'!$B$4:$B$376,A4,'Master Checklist'!$H$4:$H$376,"In Progress") -> 0 | E4: =COUNTIFS('Master Checklist'!$B$4:$B$376,A4,'Master Checklist'!$H$4:$H$376,"Pass") -> 0 | F4: =COUNTIFS('Master Checklist'!$B$4:$B$376,A4,'Master Checklist'!$H$4:$H$376,"Fail") -> 0 | G4: =IF(B4=0,0,(E4+F4)/B4) -> 0
A5: Static Analysis - APK Structure & Manifest | B5: =COUNTIF('Master Checklist'!$B$4:$B$376,A5) -> 24 | C5: =COUNTIFS('Master Checklist'!$B$4:$B$376,A5,'Master Checklist'!$H$4:$H$376,"Not Started") -> 24 | D5: =COUNTIFS('Master Checklist'!$B$4:$B$376,A5,'Master Checklist'!$H$4:$H$376,"In Progress") -> 0 | E5: =COUNTIFS('Master Checklist'!$B$4:$B$376,A5,'Master Checklist'!$H$4:$H$376,"Pass") -> 0 | F5: =COUNTIFS('Master Checklist'!$B$4:$B$376,A5,'Master Checklist'!$H$4:$H$376,"Fail") -> 0 | G5: =IF(B5=0,0,(E5+F5)/B5) -> 0
A6: Static Analysis - Code Review | B6: =COUNTIF('Master Checklist'!$B$4:$B$376,A6) -> 25 | C6: =COUNTIFS('Master Checklist'!$B$4:$B$376,A6,'Master Checklist'!$H$4:$H$376,"Not Started") -> 25 | D6: =COUNTIFS('Master Checklist'!$B$4:$B$376,A6,'Master Checklist'!$H$4:$H$376,"In Progress") -> 0 | E6: =COUNTIFS('Master Checklist'!$B$4:$B$376,A6,'Master Checklist'!$H$4:$H$376,"Pass") -> 0 | F6: =COUNTIFS('Master Checklist'!$B$4:$B$376,A6,'Master Checklist'!$H$4:$H$376,"Fail") -> 0 | G6: =IF(B6=0,0,(E6+F6)/B6) -> 0
A7: Local Data Storage | B7: =COUNTIF('Master Checklist'!$B$4:$B$376,A7) -> 25 | C7: =COUNTIFS('Master Checklist'!$B$4:$B$376,A7,'Master Checklist'!$H$4:$H$376,"Not Started") -> 25 | D7: =COUNTIFS('Master Checklist'!$B$4:$B$376,A7,'Master Checklist'!$H$4:$H$376,"In Progress") -> 0 | E7: =COUNTIFS('Master Checklist'!$B$4:$B$376,A7,'Master Checklist'!$H$4:$H$376,"Pass") -> 0 | F7: =COUNTIFS('Master Checklist'!$B$4:$B$376,A7,'Master Checklist'!$H$4:$H$376,"Fail") -> 0 | G7: =IF(B7=0,0,(E7+F7)/B7) -> 0
A8: Inter-Process Communication (IPC) | B8: =COUNTIF('Master Checklist'!$B$4:$B$376,A8) -> 29 | C8: =COUNTIFS('Master Checklist'!$B$4:$B$376,A8,'Master Checklist'!$H$4:$H$376,"Not Started") -> 29 | D8: =COUNTIFS('Master Checklist'!$B$4:$B$376,A8,'Master Checklist'!$H$4:$H$376,"In Progress") -> 0 | E8: =COUNTIFS('Master Checklist'!$B$4:$B$376,A8,'Master Checklist'!$H$4:$H$376,"Pass") -> 0 | F8: =COUNTIFS('Master Checklist'!$B$4:$B$376,A8,'Master Checklist'!$H$4:$H$376,"Fail") -> 0 | G8: =IF(B8=0,0,(E8+F8)/B8) -> 0
A9: Runtime Manipulation & Instrumentation | B9: =COUNTIF('Master Checklist'!$B$4:$B$376,A9) -> 28 | C9: =COUNTIFS('Master Checklist'!$B$4:$B$376,A9,'Master Checklist'!$H$4:$H$376,"Not Started") -> 28 | D9: =COUNTIFS('Master Checklist'!$B$4:$B$376,A9,'Master Checklist'!$H$4:$H$376,"In Progress") -> 0 | E9: =COUNTIFS('Master Checklist'!$B$4:$B$376,A9,'Master Checklist'!$H$4:$H$376,"Pass") -> 0 | F9: =COUNTIFS('Master Checklist'!$B$4:$B$376,A9,'Master Checklist'!$H$4:$H$376,"Fail") -> 0 | G9: =IF(B9=0,0,(E9+F9)/B9) -> 0
A10: Network Communication | B10: =COUNTIF('Master Checklist'!$B$4:$B$376,A10) -> 24 | C10: =COUNTIFS('Master Checklist'!$B$4:$B$376,A10,'Master Checklist'!$H$4:$H$376,"Not Started") -> 24 | D10: =COUNTIFS('Master Checklist'!$B$4:$B$376,A10,'Master Checklist'!$H$4:$H$376,"In Progress") -> 0 | E10: =COUNTIFS('Master Checklist'!$B$4:$B$376,A10,'Master Checklist'!$H$4:$H$376,"Pass") -> 0 | F10: =COUNTIFS('Master Checklist'!$B$4:$B$376,A10,'Master Checklist'!$H$4:$H$376,"Fail") -> 0 | G10: =IF(B10=0,0,(E10+F10)/B10) -> 0
A11: WebView Security | B11: =COUNTIF('Master Checklist'!$B$4:$B$376,A11) -> 22 | C11: =COUNTIFS('Master Checklist'!$B$4:$B$376,A11,'Master Checklist'!$H$4:$H$376,"Not Started") -> 22 | D11: =COUNTIFS('Master Checklist'!$B$4:$B$376,A11,'Master Checklist'!$H$4:$H$376,"In Progress") -> 0 | E11: =COUNTIFS('Master Checklist'!$B$4:$B$376,A11,'Master Checklist'!$H$4:$H$376,"Pass") -> 0 | F11: =COUNTIFS('Master Checklist'!$B$4:$B$376,A11,'Master Checklist'!$H$4:$H$376,"Fail") -> 0 | G11: =IF(B11=0,0,(E11+F11)/B11) -> 0
A12: Authentication & Session Management | B12: =COUNTIF('Master Checklist'!$B$4:$B$376,A12) -> 20 | C12: =COUNTIFS('Master Checklist'!$B$4:$B$376,A12,'Master Checklist'!$H$4:$H$376,"Not Started") -> 20 | D12: =COUNTIFS('Master Checklist'!$B$4:$B$376,A12,'Master Checklist'!$H$4:$H$376,"In Progress") -> 0 | E12: =COUNTIFS('Master Checklist'!$B$4:$B$376,A12,'Master Checklist'!$H$4:$H$376,"Pass") -> 0 | F12: =COUNTIFS('Master Checklist'!$B$4:$B$376,A12,'Master Checklist'!$H$4:$H$376,"Fail") -> 0 | G12: =IF(B12=0,0,(E12+F12)/B12) -> 0
A13: Cryptography | B13: =COUNTIF('Master Checklist'!$B$4:$B$376,A13) -> 10 | C13: =COUNTIFS('Master Checklist'!$B$4:$B$376,A13,'Master Checklist'!$H$4:$H$376,"Not Started") -> 10 | D13: =COUNTIFS('Master Checklist'!$B$4:$B$376,A13,'Master Checklist'!$H$4:$H$376,"In Progress") -> 0 | E13: =COUNTIFS('Master Checklist'!$B$4:$B$376,A13,'Master Checklist'!$H$4:$H$376,"Pass") -> 0 | F13: =COUNTIFS('Master Checklist'!$B$4:$B$376,A13,'Master Checklist'!$H$4:$H$376,"Fail") -> 0 | G13: =IF(B13=0,0,(E13+F13)/B13) -> 0
A14: Platform Interaction & Permissions | B14: =COUNTIF('Master Checklist'!$B$4:$B$376,A14) -> 15 | C14: =COUNTIFS('Master Checklist'!$B$4:$B$376,A14,'Master Checklist'!$H$4:$H$376,"Not Started") -> 15 | D14: =COUNTIFS('Master Checklist'!$B$4:$B$376,A14,'Master Checklist'!$H$4:$H$376,"In Progress") -> 0 | E14: =COUNTIFS('Master Checklist'!$B$4:$B$376,A14,'Master Checklist'!$H$4:$H$376,"Pass") -> 0 | F14: =COUNTIFS('Master Checklist'!$B$4:$B$376,A14,'Master Checklist'!$H$4:$H$376,"Fail") -> 0 | G14: =IF(B14=0,0,(E14+F14)/B14) -> 0
A15: Deep Links & App Links | B15: =COUNTIF('Master Checklist'!$B$4:$B$376,A15) -> 10 | C15: =COUNTIFS('Master Checklist'!$B$4:$B$376,A15,'Master Checklist'!$H$4:$H$376,"Not Started") -> 10 | D15: =COUNTIFS('Master Checklist'!$B$4:$B$376,A15,'Master Checklist'!$H$4:$H$376,"In Progress") -> 0 | E15: =COUNTIFS('Master Checklist'!$B$4:$B$376,A15,'Master Checklist'!$H$4:$H$376,"Pass") -> 0 | F15: =COUNTIFS('Master Checklist'!$B$4:$B$376,A15,'Master Checklist'!$H$4:$H$376,"Fail") -> 0 | G15: =IF(B15=0,0,(E15+F15)/B15) -> 0
... A23: Backend API Security (Mobile-Specific) | B23: =COUNTIF('Master Checklist'!$B$4:$B$376,A23) -> 15 | C23: =COUNTIFS('Master Checklist'!$B$4:$B$376,A23,'Master Checklist'!$H$4:$H$376,"Not Started") -> 15 | D23: =COUNTIFS('Master Checklist'!$B$4:$B$376,A23,'Master Checklist'!$H$4:$H$376,"In Progress") -> 0 | E23: =COUNTIFS('Master Checklist'!$B$4:$B$376,A23,'Master Checklist'!$H$4:$H$376,"Pass") -> 0 | F23: =COUNTIFS('Master Checklist'!$B$4:$B$376,A23,'Master Checklist'!$H$4:$H$376,"Fail") -> 0 | G23: =IF(B23=0,0,(E23+F23)/B23) -> 0
A24: TOTAL | B24: =SUM(B4:B23) -> 373 | C24: =SUM(C4:C23) -> 373 | D24: =SUM(D4:D23) -> 0 | E24: =SUM(E4:E23) -> 0 | F24: =SUM(F4:F23) -> 0 | G24: =IF(B24=0,0,(E24+F24)/B24) -> 0

Sheet Summary by Severity
A1: Summary by Severity
A3: Severity | B3: Total | C3: Not Started | D3: In Progress | E3: Pass | F3: Fail | G3: % Failed of Tested
A4: Critical | B4: =COUNTIF('Master Checklist'!$G$4:$G$376,A4) -> 9 | C4: =COUNTIFS('Master Checklist'!$G$4:$G$376,A4,'Master Checklist'!$H$4:$H$376,"Not Started") -> 9 | D4: =COUNTIFS('Master Checklist'!$G$4:$G$376,A4,'Master Checklist'!$H$4:$H$376,"In Progress") -> 0 | E4: =COUNTIFS('Master Checklist'!$G$4:$G$376,A4,'Master Checklist'!$H$4:$H$376,"Pass") -> 0 | F4: =COUNTIFS('Master Checklist'!$G$4:$G$376,A4,'Master Checklist'!$H$4:$H$376,"Fail") -> 0 | G4: =IF((E4+F4)=0,0,F4/(E4+F4)) -> 0
A5: High | B5: =COUNTIF('Master Checklist'!$G$4:$G$376,A5) -> 132 | C5: =COUNTIFS('Master Checklist'!$G$4:$G$376,A5,'Master Checklist'!$H$4:$H$376,"Not Started") -> 132 | D5: =COUNTIFS('Master Checklist'!$G$4:$G$376,A5,'Master Checklist'!$H$4:$H$376,"In Progress") -> 0 | E5: =COUNTIFS('Master Checklist'!$G$4:$G$376,A5,'Master Checklist'!$H$4:$H$376,"Pass") -> 0 | F5: =COUNTIFS('Master Checklist'!$G$4:$G$376,A5,'Master Checklist'!$H$4:$H$376,"Fail") -> 0 | G5: =IF((E5+F5)=0,0,F5/(E5+F5)) -> 0
A6: Medium | B6: =COUNTIF('Master Checklist'!$G$4:$G$376,A6) -> 170 | C6: =COUNTIFS('Master Checklist'!$G$4:$G$376,A6,'Master Checklist'!$H$4:$H$376,"Not Started") -> 170 | D6: =COUNTIFS('Master Checklist'!$G$4:$G$376,A6,'Master Checklist'!$H$4:$H$376,"In Progress") -> 0 | E6: =COUNTIFS('Master Checklist'!$G$4:$G$376,A6,'Master Checklist'!$H$4:$H$376,"Pass") -> 0 | F6: =COUNTIFS('Master Checklist'!$G$4:$G$376,A6,'Master Checklist'!$H$4:$H$376,"Fail") -> 0 | G6: =IF((E6+F6)=0,0,F6/(E6+F6)) -> 0
A7: Low | B7: =COUNTIF('Master Checklist'!$G$4:$G$376,A7) -> 25 | C7: =COUNTIFS('Master Checklist'!$G$4:$G$376,A7,'Master Checklist'!$H$4:$H$376,"Not Started") -> 25 | D7: =COUNTIFS('Master Checklist'!$G$4:$G$376,A7,'Master Checklist'!$H$4:$H$376,"In Progress") -> 0 | E7: =COUNTIFS('Master Checklist'!$G$4:$G$376,A7,'Master Checklist'!$H$4:$H$376,"Pass") -> 0 | F7: =COUNTIFS('Master Checklist'!$G$4:$G$376,A7,'Master Checklist'!$H$4:$H$376,"Fail") -> 0 | G7: =IF((E7+F7)=0,0,F7/(E7+F7)) -> 0
A8: Info | B8: =COUNTIF('Master Checklist'!$G$4:$G$376,A8) -> 37 | C8: =COUNTIFS('Master Checklist'!$G$4:$G$376,A8,'Master Checklist'!$H$4:$H$376,"Not Started") -> 37 | D8: =COUNTIFS('Master Checklist'!$G$4:$G$376,A8,'Master Checklist'!$H$4:$H$376,"In Progress") -> 0 | E8: =COUNTIFS('Master Checklist'!$G$4:$G$376,A8,'Master Checklist'!$H$4:$H$376,"Pass") -> 0 | F8: =COUNTIFS('Master Checklist'!$G$4:$G$376,A8,'Master Checklist'!$H$4:$H$376,"Fail") -> 0 | G8: =IF((E8+F8)=0,0,F8/(E8+F8)) -> 0
A9: TOTAL | B9: =SUM(B4:B8) -> 373 | C9: =SUM(C4:C8) -> 373 | D9: =SUM(D4:D8) -> 0 | E9: =SUM(E4:E8) -> 0 | F9: =SUM(F4:F8) -> 0 | G9: =IF((E9+F9)=0,0,F9/(E9+F9)) -> 0

Sheet References
A1: References & Sources
A3: Source | B3: URL | C3: Category
A4: OWASP MASTG (Mobile App Security Testing Guide) | B4: https://mas.owasp.org/MASTG/ | C4: Foundational
A5: OWASP MASVS (Mobile App Security Verification Standard) | B5: https://mas.owasp.org/MASVS/ | C5: Foundational
A6: HackTricks - Android Pentesting | B6: https://hacktricks.wiki/en/mobile-pentesting/android-checklist.html | C6: General
A7: HackTricks - Play Integrity Attestation Bypass | B7: https://hacktricks.wiki/en/mobile-pentesting/android-app-pentesting/play-integrity-attestation-bypass.html | C7: Anti-Tamper
A8: HackTricks - Bypass Biometric Authentication | B8: https://hacktricks.wiki/en/mobile-pentesting/android-app-pentesting/bypass-biometric-authentication-android.html | C8: Auth
A9: HackTricks - Task Hijacking | B9: https://hacktricks.wiki/en/mobile-pentesting/android-app-pentesting/android-task-hijacking.html | C9: IPC
A10: HackTricks - Xamarin Apps | B10: https://hacktricks.wiki/en/mobile-pentesting/xamarin-apps.html | C10: Cross-platform
A11: HackTricks - Cordova Apps | B11: https://book.hacktricks.xyz/mobile-pentesting/cordova-apps | C11: Cross-platform
A12: Hrishikesh7665 - Android Pentesting Checklist | B12: https://github.com/Hrishikesh7665/Android-Pentesting-Checklist | C12: Checklist
A13: ivan-sincek - Android Cheat Sheet | B13: https://github.com/ivan-sincek/android-penetration-testing-cheat-sheet | C13: Checklist
A14: tanprathan - Mobile App Pentest Cheatsheet | B14: https://github.com/tanprathan/mobileapp-pentest-cheatsheet | C14: Checklist
... A71: NIST NVD - CVE Database | B71: https://nvd.nist.gov/ | C71: Reference
