Workbook

Sheet Cover & Instructions
B2: Web Application Penetration Testing — Master Checklist
B3: Consolidated, deduplicated, and extended attack-surface checklist
B5: Coverage
B6: • OWASP Web Security Testing Guide (WSTG) v4.2 + v5 updates (CSV injection, security headers, concurrent sessions, client-side template injection, etc.)
B7: • OWASP Top 10 (2021) and OWASP API Security Top 10 (2023)
B8: • Bug-bounty community checklists: pentest-book, awesome-pentest-checklist, harshinsecurity, Galaxy bug-bounty, Tushar Verma's PDF, Hariprasaanth's Notion, MaverickCx 2025, e11i0t4lders0n
B9: • Mohammed Adam's bug-bounty cheatsheet (Google Sheet — referenced)
B10: • OWASP LLM Top 10 (AI-driven applications)
B11: • Modern attack research: HTTP/2 desync, browser-powered desync, single-packet race, web cache deception 2024, prototype pollution gadget chains, OAuth account-merge, and others
B12: * And few various other checklists for many pentesters and researchers.
B14: How to Use
B15: 1. Open the 'Master Checklist' sheet.
... B24: Severity Color Legend
B25: Critical | C25: Direct compromise: RCE, full account takeover, full data theft, payment fraud, root-level access
B26: High | C26: Significant compromise: privilege escalation, large data exposure, persistent XSS, SSRF to internal
B27: Medium | C27: Notable risk: missing controls, scoped data leakage, limited XSS, CSRF on minor functions
B28: Low | C28: Defense-in-depth: minor info leakage, weak headers without direct exploit
B29: Info | C29: Informational: reconnaissance findings, technology disclosure, baseline observations
B31: Disclaimer
B32: This checklist is for use in authorized engagements only. Confirm scope and rules of engagement (RoE) with the target organization before testing. Some tests (DoS, race conditions, payment tampering) may impact production systems and must only be run with explicit written authorization.

Sheet Master Checklist
A1: Web Application Penetration Testing - Master Checklist
A3: Test ID | B3: Category | C3: Test Case / Attack Vector | D3: Approach to Exploit | E3: Payloads / Examples | F3: References | G3: Severity | H3: Status | I3: Notes / Evidence
A4: WPT-01-001 | B4: 1. Reconnaissance & Information Gathering | C4: Search Engine Discovery / Google Dorking | D4: Use search engine operators to find sensitive information indexed about the target. Look for exposed credentials, internal docs, error messages, login pages, config files, backup files, and forgotten subdomains. Try multiple engines (Google, Bing, DuckDuckGo, Yandex, Baidu, Shodan, Censys, ZoomEye, FOFA, BinaryEdge). | E4: site:target.com -www | site:target.com ext:log OR ext:sql OR ext:env OR ext:bak | inurl:admin OR inurl:login OR inurl:phpinfo | intext:"index of /" site:target.com | site:pastebin.com target.com | site:github.com target.com password | F4: https://www.exploit-db.com/google-hacking-database | https://www.shodan.io | OWASP WSTG-INFO-01 | G4: Info | H4: Not Started
A5: WPT-01-002 | B5: 1. Reconnaissance & Information Gathering | C5: Web Server & Technology Fingerprinting | D5: Identify the web server, application server, frameworks, CMS, and CDN/WAF. Compare HTTP headers (Server, X-Powered-By), error pages, default file paths, cookie names, favicon hash, and JS library signatures. Check for known CVEs against detected versions. | E5: whatweb https://target.com | wappalyzer (browser ext) | nmap -sV --script=http-enum target.com | curl -sI https://target.com | nikto -h target.com | favicon hash via shodan: http.favicon.hash:-XXXXXXXX | F5: https://github.com/urbanadventurer/WhatWeb | OWASP WSTG-INFO-02 / WSTG-INFO-08 | G5: Info | H5: Not Started
A6: WPT-01-003 | B6: 1. Reconnaissance & Information Gathering | C6: Subdomain Enumeration (Passive + Active) | D6: Discover all subdomains via passive sources (CT logs, DNS DBs, search engines, archive) and active brute-forcing. Then resolve, port scan, screenshot, and look for stale/forgotten assets. Pivot via reverse-IP, ASN, organization name, JS files, and certificate SANs. | E6: subfinder -d target.com -all -recursive | amass enum -passive -d target.com | assetfinder target.com | crt.sh -d target.com | shuffledns -d target.com -w wordlist.txt -r resolvers.txt | dnsx -l subs.txt -a -resp | httpx -l subs.txt -tech-detect -title -status-code | gowitness file -f live.txt | F6: https://github.com/projectdiscovery/subfinder | https://github.com/owasp-amass/amass | https://crt.sh | G6: Info | H6: Not Started
A7: WPT-01-004 | B7: 1. Reconnaissance & Information Gathering | C7: DNS Reconnaissance (Zone transfer, AXFR, records) | D7: Enumerate DNS records (A, AAAA, MX, NS, TXT, SOA, SRV, CAA, DMARC, SPF, DKIM). Attempt AXFR (zone transfer) on each authoritative NS. Look for stale records, dangling CNAMEs (subdomain takeover), exposed staging hosts in TXT records, and SPF/DMARC misconfig enabling spoofing. | E7: dig axfr @ns1.target.com target.com | dnsrecon -d target.com -t axfr | host -t ANY target.com | dnsenum target.com | dig _dmarc.target.com TXT | F7: OWASP WSTG-INFO-04 | https://github.com/darkoperator/dnsrecon | G7: Low | H7: Not Started
A8: WPT-01-005 | B8: 1. Reconnaissance & Information Gathering | C8: Subdomain Takeover (CNAME / NS dangling) | D8: Find subdomains pointing to deprovisioned cloud services (S3, Heroku, Azure, GitHub Pages, Shopify, Fastly, Cloudfront, Tumblr, Zendesk, etc.) where you can claim the unclaimed resource and serve attacker-controlled content under the victim domain. | E8: subzy run --targets subs.txt | subjack -w subs.txt -t 100 -timeout 30 -ssl -c fingerprints.json | nuclei -t takeovers/ -l subs.txt | manually verify by registering the orphan service | F8: https://github.com/EdOverflow/can-i-take-over-xyz | OWASP WSTG-CONF-10 | G8: High | H8: Not Started
A9: WPT-01-006 | B9: 1. Reconnaissance & Information Gathering | C9: Webserver Metafiles & Hidden Path Discovery | D9: Inspect robots.txt, sitemap.xml, security.txt, humans.txt, .well-known/, ads.txt for hidden paths and disallowed dirs (often the most interesting). Mirror sitemap and crawl any unusual entries. Check archive.org/Wayback for old versions of these files. | E9: curl https://target.com/robots.txt | curl https://target.com/sitemap.xml | curl https://target.com/.well-known/security.txt | https://web.archive.org/web/*/target.com/robots.txt | F9: OWASP WSTG-INFO-03 | G9: Info | H9: Not Started
A10: WPT-01-007 | B10: 1. Reconnaissance & Information Gathering | C10: Wayback Machine & Historical Data Mining | D10: Pull historical URLs, parameters, and JS files via Wayback, CommonCrawl, AlienVault OTX, URLScan. Compare across snapshots to find removed but still-functional endpoints, leaked tokens that may be revoked but reveal patterns, deprecated parameters, and old API versions still online. | E10: waybackurls target.com | gau target.com --subs | gau --providers wayback,commoncrawl,otx,urlscan | hakrawler -url target.com | katana -u target.com | xnLinkFinder -i target.com | F10: https://github.com/tomnomnom/waybackurls | https://github.com/lc/gau | G10: Info | H10: Not Started
A11: WPT-01-008 | B11: 1. Reconnaissance & Information Gathering | C11: JavaScript Static Analysis (LinkFinder / SecretFinder) | D11: Download every JS file (including source maps if exposed). Search for: API endpoints, internal hostnames, hardcoded keys/tokens, JWT secrets, AWS/GCP/Azure keys, S3 buckets, Slack/Discord webhooks, hidden parameters, debug flags, feature flags, deprecated APIs, GraphQL introspection, comments revealing logic. | E11: subjs -i urls.txt | linkfinder -i js.txt -o cli | secretfinder -i app.js -o cli | jsleak -s -k -l -u url.txt | trufflehog filesystem ./js | grep -oE "(eyJ[a-zA-Z0-9_-]{10,}\.[a-zA-Z0-9_-]{10,}\.[a-zA-Z0-9_-]{10,}|AKIA[0-9A-Z]{16})" *.js | F11: https://github.com/GerbenJavado/LinkFinder | https://github.com/m4ll0k/SecretFinder | G11: High | H11: Not Started
A12: WPT-01-009 | B12: 1. Reconnaissance & Information Gathering | C12: Source Map / Sourcemap Disclosure (.map files) | D12: Check whether webpack/rollup/etc. .map files are exposed in production. If yes, reconstruct full TypeScript/JSX source code, internal API routes, business logic, hidden admin features, validation rules, and feature flags. | E12: curl https://target.com/static/js/main.js.map | unwebpack-sourcemap https://target.com/static/js/main.js.map ./output/ | check Network tab for any *.map response 200 | F12: https://github.com/rarecoil/unwebpack-sourcemap | G12: Medium | H12: Not Started
A13: WPT-01-010 | B13: 1. Reconnaissance & Information Gathering | C13: GitHub / GitLab / Bitbucket Recon | D13: Search code repositories belonging to the target's org and to its employees for leaked secrets, internal endpoints, infrastructure code (Terraform/Ansible), CI configs (.github/workflows), Dockerfiles, and old commits with deleted credentials still accessible via git history. | E13: gh-dorks / github-search keywords: "target.com" password | "target.com" api_key | "target.com" AWS_SECRET | trufflehog github --org=target | gitleaks detect --source ./repo | manually inspect employee profiles & forks | F13: https://github.com/trufflesecurity/trufflehog | https://github.com/zricethezav/gitleaks | G13: High | H13: Not Started
A14: WPT-01-011 | B14: 1. Reconnaissance & Information Gathering | C14: Cloud Asset & Bucket Discovery | D14: Find public S3/GCS/Azure Blob buckets, exposed Firebase databases, open Elasticsearch/Kibana, public Docker registries, exposed Kubernetes API. Often contain backups, logs, PII, configs. | E14: s3scanner scan -f buckets.txt | cloud_enum -k target | gobuster s3 -w wordlist | aws s3 ls s3://target-backups --no-sign-request | https://buckets.grayhatwarfare.com | gcpbucketbrute -k keywords.txt | F14: https://github.com/sa7mon/S3Scanner | https://github.com/initstring/cloud_enum | G14: High | H14: Not Started
A15: WPT-01-012 | B15: 1. Reconnaissance & Information Gathering | C15: Identify Application Entry Points & Attack Surface Mapping | D15: Manually walk the application + use a crawler to map every parameter, header, cookie, file upload, download, redirect, postMessage, websocket, OAuth flow, and admin/debug endpoint. Build a parameter inventory (param-miner, arjun) for hidden parameters. | E15: katana -u https://target.com -d 5 -jc | hakrawler -url target.com | arjun -u https://target.com/page -m GET -w params.txt | x8 -u https://target.com -w params.txt | param-miner (Burp ext) | F15: OWASP WSTG-INFO-06 | https://github.com/s0md3v/Arjun | G15: Info | H15: Not Started
... A254: WPT-17-004 | B254: 17. Privacy & Compliance | C254: Data Retention / Deletion Verification | D254: After 'delete account', verify all user data is removed (or anonymized) across services: DB, backups, search index, cache, logs, third-party processors. | E254: Delete account → search /api/users/me, /search?q=email → expect 404 / no results | F254: GDPR Art. 17 | G254: Medium | H254: Not Started

Sheet Summary by Category
A1: Engagement Progress Summary
A3: Category | B3: Total | C3: Not Started | D3: In Progress | E3: Pass | F3: Fail | G3: N/A | H3: % Complete
A4: 1. Reconnaissance & Information Gathering | B4: =COUNTIF('Master Checklist'!$B$4:$B$254,A4) -> 15 | C4: =COUNTIFS('Master Checklist'!$B$4:$B$254,A4,'Master Checklist'!$H$4:$H$254,"Not Started") -> 15 | D4: =COUNTIFS('Master Checklist'!$B$4:$B$254,A4,'Master Checklist'!$H$4:$H$254,"In Progress") -> 0 | E4: =COUNTIFS('Master Checklist'!$B$4:$B$254,A4,'Master Checklist'!$H$4:$H$254,"Pass") -> 0 | F4: =COUNTIFS('Master Checklist'!$B$4:$B$254,A4,'Master Checklist'!$H$4:$H$254,"Fail") -> 0 | G4: =COUNTIFS('Master Checklist'!$B$4:$B$254,A4,'Master Checklist'!$H$4:$H$254,"N/A") -> 0 | H4: =IFERROR((E4+F4+G4)/B4,0) -> 0
A5: 2. Configuration & Deployment Management | B5: =COUNTIF('Master Checklist'!$B$4:$B$254,A5) -> 14 | C5: =COUNTIFS('Master Checklist'!$B$4:$B$254,A5,'Master Checklist'!$H$4:$H$254,"Not Started") -> 14 | D5: =COUNTIFS('Master Checklist'!$B$4:$B$254,A5,'Master Checklist'!$H$4:$H$254,"In Progress") -> 0 | E5: =COUNTIFS('Master Checklist'!$B$4:$B$254,A5,'Master Checklist'!$H$4:$H$254,"Pass") -> 0 | F5: =COUNTIFS('Master Checklist'!$B$4:$B$254,A5,'Master Checklist'!$H$4:$H$254,"Fail") -> 0 | G5: =COUNTIFS('Master Checklist'!$B$4:$B$254,A5,'Master Checklist'!$H$4:$H$254,"N/A") -> 0 | H5: =IFERROR((E5+F5+G5)/B5,0) -> 0
A6: 3. Identity Management | B6: =COUNTIF('Master Checklist'!$B$4:$B$254,A6) -> 5 | C6: =COUNTIFS('Master Checklist'!$B$4:$B$254,A6,'Master Checklist'!$H$4:$H$254,"Not Started") -> 5 | D6: =COUNTIFS('Master Checklist'!$B$4:$B$254,A6,'Master Checklist'!$H$4:$H$254,"In Progress") -> 0 | E6: =COUNTIFS('Master Checklist'!$B$4:$B$254,A6,'Master Checklist'!$H$4:$H$254,"Pass") -> 0 | F6: =COUNTIFS('Master Checklist'!$B$4:$B$254,A6,'Master Checklist'!$H$4:$H$254,"Fail") -> 0 | G6: =COUNTIFS('Master Checklist'!$B$4:$B$254,A6,'Master Checklist'!$H$4:$H$254,"N/A") -> 0 | H6: =IFERROR((E6+F6+G6)/B6,0) -> 0
A7: 4. Authentication | B7: =COUNTIF('Master Checklist'!$B$4:$B$254,A7) -> 17 | C7: =COUNTIFS('Master Checklist'!$B$4:$B$254,A7,'Master Checklist'!$H$4:$H$254,"Not Started") -> 17 | D7: =COUNTIFS('Master Checklist'!$B$4:$B$254,A7,'Master Checklist'!$H$4:$H$254,"In Progress") -> 0 | E7: =COUNTIFS('Master Checklist'!$B$4:$B$254,A7,'Master Checklist'!$H$4:$H$254,"Pass") -> 0 | F7: =COUNTIFS('Master Checklist'!$B$4:$B$254,A7,'Master Checklist'!$H$4:$H$254,"Fail") -> 0 | G7: =COUNTIFS('Master Checklist'!$B$4:$B$254,A7,'Master Checklist'!$H$4:$H$254,"N/A") -> 0 | H7: =IFERROR((E7+F7+G7)/B7,0) -> 0
A8: 5. Authorization | B8: =COUNTIF('Master Checklist'!$B$4:$B$254,A8) -> 17 | C8: =COUNTIFS('Master Checklist'!$B$4:$B$254,A8,'Master Checklist'!$H$4:$H$254,"Not Started") -> 17 | D8: =COUNTIFS('Master Checklist'!$B$4:$B$254,A8,'Master Checklist'!$H$4:$H$254,"In Progress") -> 0 | E8: =COUNTIFS('Master Checklist'!$B$4:$B$254,A8,'Master Checklist'!$H$4:$H$254,"Pass") -> 0 | F8: =COUNTIFS('Master Checklist'!$B$4:$B$254,A8,'Master Checklist'!$H$4:$H$254,"Fail") -> 0 | G8: =COUNTIFS('Master Checklist'!$B$4:$B$254,A8,'Master Checklist'!$H$4:$H$254,"N/A") -> 0 | H8: =IFERROR((E8+F8+G8)/B8,0) -> 0
A9: 6. Session Management | B9: =COUNTIF('Master Checklist'!$B$4:$B$254,A9) -> 16 | C9: =COUNTIFS('Master Checklist'!$B$4:$B$254,A9,'Master Checklist'!$H$4:$H$254,"Not Started") -> 16 | D9: =COUNTIFS('Master Checklist'!$B$4:$B$254,A9,'Master Checklist'!$H$4:$H$254,"In Progress") -> 0 | E9: =COUNTIFS('Master Checklist'!$B$4:$B$254,A9,'Master Checklist'!$H$4:$H$254,"Pass") -> 0 | F9: =COUNTIFS('Master Checklist'!$B$4:$B$254,A9,'Master Checklist'!$H$4:$H$254,"Fail") -> 0 | G9: =COUNTIFS('Master Checklist'!$B$4:$B$254,A9,'Master Checklist'!$H$4:$H$254,"N/A") -> 0 | H9: =IFERROR((E9+F9+G9)/B9,0) -> 0
A10: 7. Input Validation — Injection | B10: =COUNTIF('Master Checklist'!$B$4:$B$254,A10) -> 50 | C10: =COUNTIFS('Master Checklist'!$B$4:$B$254,A10,'Master Checklist'!$H$4:$H$254,"Not Started") -> 50 | D10: =COUNTIFS('Master Checklist'!$B$4:$B$254,A10,'Master Checklist'!$H$4:$H$254,"In Progress") -> 0 | E10: =COUNTIFS('Master Checklist'!$B$4:$B$254,A10,'Master Checklist'!$H$4:$H$254,"Pass") -> 0 | F10: =COUNTIFS('Master Checklist'!$B$4:$B$254,A10,'Master Checklist'!$H$4:$H$254,"Fail") -> 0 | G10: =COUNTIFS('Master Checklist'!$B$4:$B$254,A10,'Master Checklist'!$H$4:$H$254,"N/A") -> 0 | H10: =IFERROR((E10+F10+G10)/B10,0) -> 0
A11: 8. Cryptography | B11: =COUNTIF('Master Checklist'!$B$4:$B$254,A11) -> 9 | C11: =COUNTIFS('Master Checklist'!$B$4:$B$254,A11,'Master Checklist'!$H$4:$H$254,"Not Started") -> 9 | D11: =COUNTIFS('Master Checklist'!$B$4:$B$254,A11,'Master Checklist'!$H$4:$H$254,"In Progress") -> 0 | E11: =COUNTIFS('Master Checklist'!$B$4:$B$254,A11,'Master Checklist'!$H$4:$H$254,"Pass") -> 0 | F11: =COUNTIFS('Master Checklist'!$B$4:$B$254,A11,'Master Checklist'!$H$4:$H$254,"Fail") -> 0 | G11: =COUNTIFS('Master Checklist'!$B$4:$B$254,A11,'Master Checklist'!$H$4:$H$254,"N/A") -> 0 | H11: =IFERROR((E11+F11+G11)/B11,0) -> 0
A12: 9. Business Logic | B12: =COUNTIF('Master Checklist'!$B$4:$B$254,A12) -> 15 | C12: =COUNTIFS('Master Checklist'!$B$4:$B$254,A12,'Master Checklist'!$H$4:$H$254,"Not Started") -> 15 | D12: =COUNTIFS('Master Checklist'!$B$4:$B$254,A12,'Master Checklist'!$H$4:$H$254,"In Progress") -> 0 | E12: =COUNTIFS('Master Checklist'!$B$4:$B$254,A12,'Master Checklist'!$H$4:$H$254,"Pass") -> 0 | F12: =COUNTIFS('Master Checklist'!$B$4:$B$254,A12,'Master Checklist'!$H$4:$H$254,"Fail") -> 0 | G12: =COUNTIFS('Master Checklist'!$B$4:$B$254,A12,'Master Checklist'!$H$4:$H$254,"N/A") -> 0 | H12: =IFERROR((E12+F12+G12)/B12,0) -> 0
A13: 10. Client-Side | B13: =COUNTIF('Master Checklist'!$B$4:$B$254,A13) -> 12 | C13: =COUNTIFS('Master Checklist'!$B$4:$B$254,A13,'Master Checklist'!$H$4:$H$254,"Not Started") -> 12 | D13: =COUNTIFS('Master Checklist'!$B$4:$B$254,A13,'Master Checklist'!$H$4:$H$254,"In Progress") -> 0 | E13: =COUNTIFS('Master Checklist'!$B$4:$B$254,A13,'Master Checklist'!$H$4:$H$254,"Pass") -> 0 | F13: =COUNTIFS('Master Checklist'!$B$4:$B$254,A13,'Master Checklist'!$H$4:$H$254,"Fail") -> 0 | G13: =COUNTIFS('Master Checklist'!$B$4:$B$254,A13,'Master Checklist'!$H$4:$H$254,"N/A") -> 0 | H13: =IFERROR((E13+F13+G13)/B13,0) -> 0
A14: 11. API Security | B14: =COUNTIF('Master Checklist'!$B$4:$B$254,A14) -> 15 | C14: =COUNTIFS('Master Checklist'!$B$4:$B$254,A14,'Master Checklist'!$H$4:$H$254,"Not Started") -> 15 | D14: =COUNTIFS('Master Checklist'!$B$4:$B$254,A14,'Master Checklist'!$H$4:$H$254,"In Progress") -> 0 | E14: =COUNTIFS('Master Checklist'!$B$4:$B$254,A14,'Master Checklist'!$H$4:$H$254,"Pass") -> 0 | F14: =COUNTIFS('Master Checklist'!$B$4:$B$254,A14,'Master Checklist'!$H$4:$H$254,"Fail") -> 0 | G14: =COUNTIFS('Master Checklist'!$B$4:$B$254,A14,'Master Checklist'!$H$4:$H$254,"N/A") -> 0 | H14: =IFERROR((E14+F14+G14)/B14,0) -> 0
A15: 12. Supply Chain & Software Integrity | B15: =COUNTIF('Master Checklist'!$B$4:$B$254,A15) -> 6 | C15: =COUNTIFS('Master Checklist'!$B$4:$B$254,A15,'Master Checklist'!$H$4:$H$254,"Not Started") -> 6 | D15: =COUNTIFS('Master Checklist'!$B$4:$B$254,A15,'Master Checklist'!$H$4:$H$254,"In Progress") -> 0 | E15: =COUNTIFS('Master Checklist'!$B$4:$B$254,A15,'Master Checklist'!$H$4:$H$254,"Pass") -> 0 | F15: =COUNTIFS('Master Checklist'!$B$4:$B$254,A15,'Master Checklist'!$H$4:$H$254,"Fail") -> 0 | G15: =COUNTIFS('Master Checklist'!$B$4:$B$254,A15,'Master Checklist'!$H$4:$H$254,"N/A") -> 0 | H15: =IFERROR((E15+F15+G15)/B15,0) -> 0
... A20: 17. Privacy & Compliance | B20: =COUNTIF('Master Checklist'!$B$4:$B$254,A20) -> 4 | C20: =COUNTIFS('Master Checklist'!$B$4:$B$254,A20,'Master Checklist'!$H$4:$H$254,"Not Started") -> 4 | D20: =COUNTIFS('Master Checklist'!$B$4:$B$254,A20,'Master Checklist'!$H$4:$H$254,"In Progress") -> 0 | E20: =COUNTIFS('Master Checklist'!$B$4:$B$254,A20,'Master Checklist'!$H$4:$H$254,"Pass") -> 0 | F20: =COUNTIFS('Master Checklist'!$B$4:$B$254,A20,'Master Checklist'!$H$4:$H$254,"Fail") -> 0 | G20: =COUNTIFS('Master Checklist'!$B$4:$B$254,A20,'Master Checklist'!$H$4:$H$254,"N/A") -> 0 | H20: =IFERROR((E20+F20+G20)/B20,0) -> 0
A21: TOTAL | B21: =SUM(B4:B20) -> 251 | C21: =SUM(C4:C20) -> 251 | D21: =SUM(D4:D20) -> 0 | E21: =SUM(E4:E20) -> 0 | F21: =SUM(F4:F20) -> 0 | G21: =SUM(G4:G20) -> 0 | H21: =IFERROR((E21+F21+G21)/B21,0) -> 0

Sheet Summary by Severity
A1: Findings by Severity
A3: Severity | B3: Total Tests | C3: Tested (Pass+Fail+N/A) | D3: Failed (Findings) | E3: % Failed of Tested
A4: Critical | B4: =COUNTIF('Master Checklist'!$G$4:$G$254,A4) -> 82 | C4: =COUNTIFS('Master Checklist'!$G$4:$G$254,A4,'Master Checklist'!$H$4:$H$254,"Pass")+COUNTIFS('Master Checklist'!$G$4:$G$254,A4,'Master Checklist'!$H$4:$H$254,"Fail")+COUNTIFS('Master Checklist'!$G$4:$G$254,A4,'Master Checklist'!$H$4:$H$254,"N/A") -> 0 | D4: =COUNTIFS('Master Checklist'!$G$4:$G$254,A4,'Master Checklist'!$H$4:$H$254,"Fail") -> 0 | E4: =IFERROR(D4/C4,0) -> 0
A5: High | B5: =COUNTIF('Master Checklist'!$G$4:$G$254,A5) -> 99 | C5: =COUNTIFS('Master Checklist'!$G$4:$G$254,A5,'Master Checklist'!$H$4:$H$254,"Pass")+COUNTIFS('Master Checklist'!$G$4:$G$254,A5,'Master Checklist'!$H$4:$H$254,"Fail")+COUNTIFS('Master Checklist'!$G$4:$G$254,A5,'Master Checklist'!$H$4:$H$254,"N/A") -> 0 | D5: =COUNTIFS('Master Checklist'!$G$4:$G$254,A5,'Master Checklist'!$H$4:$H$254,"Fail") -> 0 | E5: =IFERROR(D5/C5,0) -> 0
A6: Medium | B6: =COUNTIF('Master Checklist'!$G$4:$G$254,A6) -> 53 | C6: =COUNTIFS('Master Checklist'!$G$4:$G$254,A6,'Master Checklist'!$H$4:$H$254,"Pass")+COUNTIFS('Master Checklist'!$G$4:$G$254,A6,'Master Checklist'!$H$4:$H$254,"Fail")+COUNTIFS('Master Checklist'!$G$4:$G$254,A6,'Master Checklist'!$H$4:$H$254,"N/A") -> 0 | D6: =COUNTIFS('Master Checklist'!$G$4:$G$254,A6,'Master Checklist'!$H$4:$H$254,"Fail") -> 0 | E6: =IFERROR(D6/C6,0) -> 0
A7: Low | B7: =COUNTIF('Master Checklist'!$G$4:$G$254,A7) -> 10 | C7: =COUNTIFS('Master Checklist'!$G$4:$G$254,A7,'Master Checklist'!$H$4:$H$254,"Pass")+COUNTIFS('Master Checklist'!$G$4:$G$254,A7,'Master Checklist'!$H$4:$H$254,"Fail")+COUNTIFS('Master Checklist'!$G$4:$G$254,A7,'Master Checklist'!$H$4:$H$254,"N/A") -> 0 | D7: =COUNTIFS('Master Checklist'!$G$4:$G$254,A7,'Master Checklist'!$H$4:$H$254,"Fail") -> 0 | E7: =IFERROR(D7/C7,0) -> 0
A8: Info | B8: =COUNTIF('Master Checklist'!$G$4:$G$254,A8) -> 7 | C8: =COUNTIFS('Master Checklist'!$G$4:$G$254,A8,'Master Checklist'!$H$4:$H$254,"Pass")+COUNTIFS('Master Checklist'!$G$4:$G$254,A8,'Master Checklist'!$H$4:$H$254,"Fail")+COUNTIFS('Master Checklist'!$G$4:$G$254,A8,'Master Checklist'!$H$4:$H$254,"N/A") -> 0 | D8: =COUNTIFS('Master Checklist'!$G$4:$G$254,A8,'Master Checklist'!$H$4:$H$254,"Fail") -> 0 | E8: =IFERROR(D8/C8,0) -> 0

Sheet References
A1: Source Materials & References
A3: Source / Resource | B3: URL
A4: OWASP Web Security Testing Guide (WSTG) | B4: https://owasp.org/www-project-web-security-testing-guide/
A5: OWASP Top 10 (2021) | B5: https://owasp.org/Top10/
A6: OWASP API Security Top 10 (2023) | B6: https://owasp.org/API-Security/editions/2023/en/0x00-header/
A7: OWASP Top 10 for LLM Applications | B7: https://owasp.org/www-project-top-10-for-large-language-model-applications/
A8: OWASP Cheat Sheet Series | B8: https://cheatsheetseries.owasp.org/
A9: OWASP Secure Headers Project | B9: https://owasp.org/www-project-secure-headers/
A10: PortSwigger Web Security Academy | B10: https://portswigger.net/web-security
A11: PortSwigger Research (Smashing the State Machine, HTTP/2, Cache, ...) | B11: https://portswigger.net/research
A12: Awesome Pentest Checklist (iAnonymous3000) | B12: https://github.com/iAnonymous3000/awesome-pentest-checklist
A13: Web Pentesting Checklist (harshinsecurity) | B13: https://github.com/harshinsecurity/web-pentesting-checklist
A14: Pentest-Book Web Checklist (carlospolop / community) | B14: https://www.pentest-book.com/others/web-checklist
... A31: Browser-Powered Desync Attacks (Kettle, 2024) | B31: https://portswigger.net/research/browser-powered-desync-attacks
